[
    {
        "month":"Jan",
        "newUsers":10,
        "totalUsers":10
    },
    {
        "month":"Feb",
        "newUsers":20,
        "totalUsers":30
    },
    {
        "month":"Mar",
        "newUsers":5,
        "totalUsers":35
    },
    {
        "month":"Apr",
        "newUsers":0,
        "totalUsers":35
    },
    {
        "month":"May",
        "newUsers":27,
        "totalUsers":62
    },
    {
        "month":"Jun",
        "newUsers":10,
        "totalUsers":72
    },
    {
        "month":"Jul",
        "newUsers":0,
        "totalUsers":72
    },
    {
        "month":"Jul",
        "newUsers":18,
        "totalUsers":90
    },
    {
        "month":"Aug",
        "newUsers":9,
        "totalUsers":99
    },
    {
        "month":"Sep",
        "newUsers":18,
        "totalUsers":117
    },
    {
        "month":"Oct",
        "newUsers":1,
        "totalUsers":118
    },
    {
        "month":"Nov",
        "newUsers":22,
        "totalUsers":140
    },
    {
        "month":"Dec",
        "newUsers":10,
        "totalUsers":150
    }
]